19,28c19,20
<     <field name="unittitle_ssm">
<       Roiz Gomez, Eliseo
<       
<       Roiz Gomez, Marina (née Pando)
<     </field>
<     <field name="unittitle_teim">
<       Roiz Gomez, Eliseo
<       
<       Roiz Gomez, Marina (née Pando)
<     </field>
---
>     <field name="unittitle_ssm">Roiz Gomez, EliseoRoiz Gomez, Marina (née Pando)</field>
>     <field name="unittitle_teim">Roiz Gomez, EliseoRoiz Gomez, Marina (née Pando)</field>
57,66c49,50
<     <field name="series_si">Series I: Case Files &gt;&gt; Sub-Series A: Spanish Refugee Aid Case Files &gt;&gt; 
<       Roiz Gomez, Eliseo
<       
<       Roiz Gomez, Marina (née Pando)
<     </field>
<     <field name="heading_ssm">
<       Roiz Gomez, Eliseo
<       
<       Roiz Gomez, Marina (née Pando)
<     </field>
---
>     <field name="series_si">Series I: Case Files &gt;&gt; Sub-Series A: Spanish Refugee Aid Case Files &gt;&gt; Roiz Gomez, EliseoRoiz Gomez, Marina (née Pando)</field>
>     <field name="heading_ssm">Roiz Gomez, EliseoRoiz Gomez, Marina (née Pando)</field>
