diff golden [PRETTIFIED] actual [PRETTIFIED]
--- golden [PRETTIFIED]
+++ actual [PRETTIFIED]
@@ -31,6 +31,7 @@
     <field name="format_sim">Archival Object</field>
     <field name="format_ssm">Archival Object</field>
     <field name="location_ssm">Box: 166, Cassette: 255</field>
+    <field name="location_ssm">Box: 166, Cassette: 255</field>
     <field name="location_ssm">Box: 165, Cassette: 255</field>
     <field name="location_si">Box: 165, Cassette: 255</field>
     <field name="collection_teim">The Paper Tiger Television Archive</field>
